{
  "format_version": "1.12",
  "minecraft:recipe_shaped": {
    "description": {
    "identifier": "minecraft:golden_carrot"
    },

    
    "tags": [ "crafting_table" ],
    "pattern": [
      "#N#",
      "NXN",
      "#N#"
    ],
    "key": {
      "#": {
        "item": "minecraft:gold_ingot"
      },
      "X": {
        "item": "minecraft:carrot"
      },
      "N": {
        "item": "minecraft:gold_nugget"
      }
    },
    "result": {
      "item": "minecraft:golden_carrot",
      "count": 2
    }
  }
}
